extra_utils/__init__.py
extra_utils/b站词云.py
extra_utils/decorator_util.py
extra_utils/django_operation.py
extra_utils/numpy_operations.py
extra_utils/pandas_operations.py
extra_utils/re_util.py
extra_utils/variable_name_util.py
extra_utils-0.0.6.dist-info/LICENSE
extra_utils-0.0.6.dist-info/METADATA
extra_utils-0.0.6.dist-info/WHEEL
extra_utils-0.0.6.dist-info/top_level.txt
extra_utils-0.0.6.dist-info/RECORD
