Metadata-Version: 2.1
Name: extra-utils
Version: 0.0.6
Summary: Short description
Home-page: https://gitee.com/SkyOceanchen/extra_utils.git
Author: SkyOceanChen
Author-email: skyoceanchen@foxmail.com
Maintainer: SkyOceanChen
Maintainer-email: skyoceanchen@foxmail.com
License: MIT
Classifier: Development Status :: 3 - Alpha
Classifier: Intended Audience :: Developers
Classifier: Operating System :: OS Independent
Classifier: Topic :: Software Development :: Build Tools
Classifier: License :: OSI Approved :: MIT License
Classifier: Programming Language :: Python :: 3.6
Classifier: Programming Language :: Python :: 3.8
Classifier: Programming Language :: Python :: 3.10
Requires-Python: ~=3.3
License-File: LICENSE
Requires-Dist: basic-type-operations
Requires-Dist: django (==4.2.3)
